cirrus/plugins/docs/__init__.py
cirrus/plugins/docs/base_conf.py
cirrus/plugins/docs/builder.py
cirrus/plugins/docs/commands.py
cirrus/plugins/docs/compiler.py
cirrus/plugins/docs/constants.py
cirrus/plugins/docs/templater.py
cirrus/plugins/docs/utils.py
cirrus/plugins/docs/docs/__init__.py
cirrus/plugins/docs/docs/conf.py
cirrus/plugins/docs/docs/index.rst
cirrus/plugins/docs/docs/_extra/.gitkeep
cirrus/plugins/docs/docs/_static/js/versions-loader.js
cirrus/plugins/docs/docs/_templates/versions.html
cirrus_docs-0.2.0.dist-info/METADATA
cirrus_docs-0.2.0.dist-info/WHEEL
cirrus_docs-0.2.0.dist-info/dependency_links.txt
cirrus_docs-0.2.0.dist-info/entry_points.txt
cirrus_docs-0.2.0.dist-info/top_level.txt
cirrus_docs-0.2.0.dist-info/RECORD
