Metadata-Version: 2.1
Name: cirrus-docs
Version: 0.2.0
Summary: Utilities to manage cirrus project documentation.
Home-page: https://github.com/cirrus-geo/cirrus-docs
Author: Jarrett Keifer (jkeifer), Element 84
License: Apache-2.0
Classifier: Intended Audience :: Developers
Classifier: License :: OSI Approved :: Apache Software License
Classifier: Programming Language :: Python :: 3.9
Classifier: Programming Language :: Python :: 3.10
Classifier: Programming Language :: Python :: 3.11
Requires-Python: >=3.9
Requires-Dist: cirrus-geo ~=0.10.0
Requires-Dist: sphinx ~=7.2.0
Requires-Dist: myst-parser ~=2.0.0
Requires-Dist: sphinxcontrib-mermaid ~=0.9.2
Requires-Dist: click-option-group ~=0.5.6
Requires-Dist: sphinx-click ~=5.1.0
